{
	"configurations" : 
	[
		{
			"directories" : 
			[
				{
					"build" : ".",
					"childIndexes" : 
					[
						1,
						2
					],
					"jsonFile" : "directory-.-Debug-d0094a50bb2071803777.json",
					"minimumCMakeVersion" : 
					{
						"string" : "3.19"
					},
					"projectIndex" : 0,
					"source" : "."
				},
				{
					"build" : "dependencies",
					"jsonFile" : "directory-dependencies-Debug-213773dd22be3796fa39.json",
					"minimumCMakeVersion" : 
					{
						"string" : "3.19"
					},
					"parentIndex" : 0,
					"projectIndex" : 0,
					"source" : "dependencies"
				},
				{
					"build" : "gab-engine",
					"childIndexes" : 
					[
						3,
						10,
						11,
						12
					],
					"jsonFile" : "directory-gab-engine-Debug-4b0f5e51ca788c205107.json",
					"minimumCMakeVersion" : 
					{
						"string" : "3.19"
					},
					"parentIndex" : 0,
					"projectIndex" : 0,
					"source" : "gab-engine",
					"targetIndexes" : 
					[
						10
					]
				},
				{
					"build" : "gab-engine/Editor",
					"childIndexes" : 
					[
						4,
						5,
						6,
						7,
						8,
						9
					],
					"jsonFile" : "directory-gab-engine.Editor-Debug-b1448a80a17b91e57fd4.json",
					"minimumCMakeVersion" : 
					{
						"string" : "3.19"
					},
					"parentIndex" : 2,
					"projectIndex" : 0,
					"source" : "gab-engine/Editor",
					"targetIndexes" : 
					[
						1
					]
				},
				{
					"build" : "gab-engine/Editor/Component",
					"jsonFile" : "directory-gab-engine.Editor.Component-Debug-88c15addf92e7eaa219e.json",
					"minimumCMakeVersion" : 
					{
						"string" : "3.19"
					},
					"parentIndex" : 3,
					"projectIndex" : 0,
					"source" : "gab-engine/Editor/Component",
					"targetIndexes" : 
					[
						2
					]
				},
				{
					"build" : "gab-engine/Editor/Global",
					"jsonFile" : "directory-gab-engine.Editor.Global-Debug-5c18eff55a81f25f8b2a.json",
					"minimumCMakeVersion" : 
					{
						"string" : "3.19"
					},
					"parentIndex" : 3,
					"projectIndex" : 0,
					"source" : "gab-engine/Editor/Global",
					"targetIndexes" : 
					[
						3
					]
				},
				{
					"build" : "gab-engine/Editor/Input",
					"jsonFile" : "directory-gab-engine.Editor.Input-Debug-724ceb3795b0192c6d06.json",
					"minimumCMakeVersion" : 
					{
						"string" : "3.19"
					},
					"parentIndex" : 3,
					"projectIndex" : 0,
					"source" : "gab-engine/Editor/Input",
					"targetIndexes" : 
					[
						4
					]
				},
				{
					"build" : "gab-engine/Editor/ObjectFunctions",
					"jsonFile" : "directory-gab-engine.Editor.ObjectFunctions-Debug-0ea5c87cb2dc3aeaf285.json",
					"minimumCMakeVersion" : 
					{
						"string" : "3.19"
					},
					"parentIndex" : 3,
					"projectIndex" : 0,
					"source" : "gab-engine/Editor/ObjectFunctions",
					"targetIndexes" : 
					[
						5
					]
				},
				{
					"build" : "gab-engine/Editor/ObjectHandlers",
					"jsonFile" : "directory-gab-engine.Editor.ObjectHandlers-Debug-9cb55673033a09b6c702.json",
					"minimumCMakeVersion" : 
					{
						"string" : "3.19"
					},
					"parentIndex" : 3,
					"projectIndex" : 0,
					"source" : "gab-engine/Editor/ObjectHandlers",
					"targetIndexes" : 
					[
						6
					]
				},
				{
					"build" : "gab-engine/Editor/Objects",
					"jsonFile" : "directory-gab-engine.Editor.Objects-Debug-0214f3d1931b8ad38b99.json",
					"minimumCMakeVersion" : 
					{
						"string" : "3.19"
					},
					"parentIndex" : 3,
					"projectIndex" : 0,
					"source" : "gab-engine/Editor/Objects",
					"targetIndexes" : 
					[
						7
					]
				},
				{
					"build" : "gab-engine/Datatypes",
					"jsonFile" : "directory-gab-engine.Datatypes-Debug-5cee633915dc9789d1d0.json",
					"minimumCMakeVersion" : 
					{
						"string" : "3.19"
					},
					"parentIndex" : 2,
					"projectIndex" : 0,
					"source" : "gab-engine/Datatypes",
					"targetIndexes" : 
					[
						0
					]
				},
				{
					"build" : "gab-engine/Graphics",
					"jsonFile" : "directory-gab-engine.Graphics-Debug-5cedf57a3d68260650a4.json",
					"minimumCMakeVersion" : 
					{
						"string" : "3.19"
					},
					"parentIndex" : 2,
					"projectIndex" : 0,
					"source" : "gab-engine/Graphics",
					"targetIndexes" : 
					[
						8
					]
				},
				{
					"build" : "gab-engine/Window",
					"jsonFile" : "directory-gab-engine.Window-Debug-832f88ee9f67a6f2877e.json",
					"minimumCMakeVersion" : 
					{
						"string" : "3.0"
					},
					"parentIndex" : 2,
					"projectIndex" : 0,
					"source" : "gab-engine/Window",
					"targetIndexes" : 
					[
						9
					]
				}
			],
			"name" : "Debug",
			"projects" : 
			[
				{
					"directoryIndexes" : 
					[
						0,
						1,
						2,
						3,
						4,
						5,
						6,
						7,
						8,
						9,
						10,
						11,
						12
					],
					"name" : "gab-engine",
					"targetIndexes" : 
					[
						0,
						1,
						2,
						3,
						4,
						5,
						6,
						7,
						8,
						9,
						10
					]
				}
			],
			"targets" : 
			[
				{
					"directoryIndex" : 10,
					"id" : "Datatypes::@b70552011a10632480bf",
					"jsonFile" : "target-Datatypes-Debug-3ee8582fc53f84a8d3eb.json",
					"name" : "Datatypes",
					"projectIndex" : 0
				},
				{
					"directoryIndex" : 3,
					"id" : "Editor::@4d78af1c25011d69889b",
					"jsonFile" : "target-Editor-Debug-f1a3dc1a4a28cfda53f2.json",
					"name" : "Editor",
					"projectIndex" : 0
				},
				{
					"directoryIndex" : 4,
					"id" : "Editor-Component::@530430e3cfedeaac280a",
					"jsonFile" : "target-Editor-Component-Debug-a8199510f3601fcfb6cc.json",
					"name" : "Editor-Component",
					"projectIndex" : 0
				},
				{
					"directoryIndex" : 5,
					"id" : "Editor-Global::@89efd496c40152f8acb0",
					"jsonFile" : "target-Editor-Global-Debug-41b4ceb4021c6ccb5f32.json",
					"name" : "Editor-Global",
					"projectIndex" : 0
				},
				{
					"directoryIndex" : 6,
					"id" : "Editor-Input::@4bfc1280be3f88fd5b94",
					"jsonFile" : "target-Editor-Input-Debug-34b44dcf0f316e4cb3fa.json",
					"name" : "Editor-Input",
					"projectIndex" : 0
				},
				{
					"directoryIndex" : 7,
					"id" : "Editor-ObjectFunctions::@0fc55c07c65a72534e0c",
					"jsonFile" : "target-Editor-ObjectFunctions-Debug-956188791cc904334435.json",
					"name" : "Editor-ObjectFunctions",
					"projectIndex" : 0
				},
				{
					"directoryIndex" : 8,
					"id" : "Editor-ObjectHandlers::@4b9e948f5523d70c556e",
					"jsonFile" : "target-Editor-ObjectHandlers-Debug-5b1446ffe37a290a62c9.json",
					"name" : "Editor-ObjectHandlers",
					"projectIndex" : 0
				},
				{
					"directoryIndex" : 9,
					"id" : "Editor-Objects::@26d29d9515c5e1ad322e",
					"jsonFile" : "target-Editor-Objects-Debug-a983dddea69e5bc6dee8.json",
					"name" : "Editor-Objects",
					"projectIndex" : 0
				},
				{
					"directoryIndex" : 11,
					"id" : "Graphics::@c358c1132ce34b077aef",
					"jsonFile" : "target-Graphics-Debug-3aaefc9148c77268f139.json",
					"name" : "Graphics",
					"projectIndex" : 0
				},
				{
					"directoryIndex" : 12,
					"id" : "Window::@21f87f48f34a169b5933",
					"jsonFile" : "target-Window-Debug-28a5643ec59d32d9eb0d.json",
					"name" : "Window",
					"projectIndex" : 0
				},
				{
					"directoryIndex" : 2,
					"id" : "gab-engine::@3f8e890217629a2f377b",
					"jsonFile" : "target-gab-engine-Debug-e6bbeb5ebbce4f3bdbfe.json",
					"name" : "gab-engine",
					"projectIndex" : 0
				}
			]
		}
	],
	"kind" : "codemodel",
	"paths" : 
	{
		"build" : "D:/Documents/GitHub/Gab-Engine/gab-engine/out/build/x64-debug",
		"source" : "D:/Documents/GitHub/Gab-Engine/gab-engine"
	},
	"version" : 
	{
		"major" : 2,
		"minor" : 7
	}
}
